pybookmd/__init__.py
pybookmd/cli.py
pybookmd/exceptions.py
pybookmd/generators/__init__.py
pybookmd/generators/base_generator.py
pybookmd/generators/pdf_generator.py
pybookmd/hash.py
pybookmd-1.0.12.dist-info/entry_points.txt
pybookmd-1.0.12.dist-info/WHEEL
pybookmd-1.0.12.dist-info/METADATA
pybookmd-1.0.12.dist-info/RECORD
