Metadata-Version: 2.1
Name: pybookmd
Version: 1.0.12
Summary: "Simple book building CLI for markdown based books"
License: MIT
Author: Dylan Kirby
Author-email: dylankirbydev@outlook.com
Requires-Python: >=3.6,<4.0
Classifier: License :: OSI Approved :: MIT License
Classifier: Programming Language :: Python :: 3
Classifier: Programming Language :: Python :: 3.6
Classifier: Programming Language :: Python :: 3.7
Classifier: Programming Language :: Python :: 3.8
Classifier: Programming Language :: Python :: 3.9
Requires-Dist: click (>=8.0.3,<9.0.0)
Requires-Dist: fastcore (==1.3.19)
Requires-Dist: packaging (==20.9)
Requires-Dist: pypandoc (==1.5)
Requires-Dist: pyparsing (==2.4.7)
